
<annotation>
    <folder>French fries</folder>
    <filename>1fa8385175e871f1.jpg</filename>
    <path>/path/to/the/file/1fa8385175e871f1.jpg</path>
    <source>
        <database>Unknown</database>
    </source>
    <size>
        <width>1024</width>
        <height>1024</height>
        <depth>3</depth>
    </size>
    <segmented>0</segmented>
    <object>
        <name>French fries</name>
        <pose>Unspecified</pose>
        <truncated>0</truncated>
        <difficult>0</difficult>
        <bndbox>
            <xmin>284</xmin>
            <ymin>35</ymin>
            <xmax>1024</xmax>
            <ymax>823</ymax>
        </bndbox>
    </object>

</annotation>
